{
  "posts": [
    {
      "id": "c84f",
      "pseudo": "From Scratch",
      "message": "Yo les gens"
    }
  ],
  "users": [
    {
      "id": "1607",
      "pseudo": "From Scratch",
      "age": 25
    },
    {
      "id": "be4d",
      "pseudo": "Barbapapa",
      "email": "barbapapa@gmail.com",
      "password": "Barbapapa96-"
    },
    {
      "id": "d0f1",
      "pseudo": "dazdza",
      "email": "azdazd@zadaz.com",
      "password": "azdazd"
    },
    {
      "id": "8f0d",
      "pseudo": "azdazd",
      "email": "azdazdazd@ezfzefez.com",
      "password": "adzad"
    },
    {
      "id": "099c",
      "pseudo": "azdazdazdazd",
      "email": "dazdazdazdazdazdaz@gmail.com",
      "password": "dzad"
    },
    {
      "id": "d2f2",
      "pseudo": "azdazdazd",
      "email": "azdazdazdazd@gmail.com",
      "password": "Tetard8596-"
    },
    {
      "id": "46af",
      "pseudo": "zzzz",
      "email": "azdazd@zeffzef.com",
      "password": "Tetard8596-"
    }
  ]
}